{"title":"Speaking Experience","organization":null,"section":"Technical Skills","from":null,"to":null,"location":null,"category":"resume","robots":"noindex, nofollow","layout":"default","url":"/0001/03/01/speaking-experience/","date":"0001-03-01 00:00:00 -0500","id":"/0001/03/01/speaking-experience","categories":["resume"],"next":"*   Expertise in modern web development methods (HTML, CSS, Javascript, MySQL, PHP); enterprise system architecture; application programing interfaces (APIs); WordPress management, development, and integration; search engine optimization; Google Analytics; and Unix system administration.\n*   Lead development of six active open-source projects with more than 60,000 downloads to date.","previous":"","tags":[],"content":"<ul>\n<li><a href='http://sxsw.com'>South by Southwest</a> Interactive, panelist, <a href='http://panelpicker.sxsw.com/ideas/view/10270'>Content and Coding are not Commodities</a></li>\n\n<li>Guest lecturer, American University, <a href='http://ben.balter.com/2011/03/09/craft-your-personal-brand/'>Personal Branding and Social Media</a></li>\n\n<li><a href='http://crushIQ.com'>CrushIQ</a>, speaker, <a href='http://ben.balter.com/2011/11/14/making-wordpress-more-shareable-sociable-and-likeable/' rel='bookmark' title='Making WordPress More Shareable, Sociable, and Likeable'>Making WordPress More Shareable, Sociable, and Likeable</a>.</li>\n\n<li>Social Media Summit, panelist, <a href='http://sls2012.sched.org/event/17d29cfcb8dcba402bfc0b75368e15ae'>The Digital Me: Personal Branding</a></li>\n\n<li>Present regularly at<a href='http://ben.balter.com/2011/04/12/love-the-code/'>local technology</a> meetups including Hacks/Hackers DC and WordPress DC</li>\n</ul>"}