{"author":"Benjamin J. Balter","title":"How I Learned to Stop Worrying and Love the Code\n","excerpt":"I am gave a brief lightning talk at April's WordPress DC Meetup on the basics of HTML and PHP (\"coding for dummies\"). The goal: learn how to avoid breaking your website if you edit it. Below are the slides and recording.\n","layout":"post","categories":["Technology"],"tags":["code","open source","presentation","wordpress"],"post_format":[],"related_posts":[{"url":"/2010/09/12/wordpress-resume-plugin/","id":"/2010/09/12/wordpress-resume-plugin","title":"WordPress Resume Plugin"},{"url":"/2010/09/13/new-media-flak-megaphone-vs-cocktail-party/","id":"/2010/09/13/new-media-flak-megaphone-vs-cocktail-party","title":"New Media Flak: Megaphone vs. Cocktail Party"},{"url":"/2010/10/10/does-every-cloud-have-a-silver-lining/","id":"/2010/10/10/does-every-cloud-have-a-silver-lining","title":"Does Every Cloud Have a Silver Lining?"},{"url":"/2010/11/06/removing-the-barriers-to-organizational-agility/","id":"/2010/11/06/removing-the-barriers-to-organizational-agility","title":"Removing the Barriers to Organizational Agility\n"},{"url":"/2010/11/08/what-fourteen-century-apple-pie-teaches-us-about-sharing/","id":"/2010/11/08/what-fourteen-century-apple-pie-teaches-us-about-sharing","title":"What Fourteen-Century Apple Pie Teaches Us About Sharing\n"},{"url":"/2010/11/15/will-federal-contracting-officers-soon-have-their-heads-in-the-clouds/","id":"/2010/11/15/will-federal-contracting-officers-soon-have-their-heads-in-the-clouds","title":"Will Federal Contracting Officers Soon Have Their Heads in the Clouds?\n"},{"url":"/2010/11/29/free-trade-in-china-just-google-it/","id":"/2010/11/29/free-trade-in-china-just-google-it","title":"Free Trade in China? Just Google it."},{"url":"/2010/11/29/twitter-mentions-as-comments/","id":"/2010/11/29/twitter-mentions-as-comments","title":"Twitter Mentions as Comments WordPress Plugin\n"},{"url":"/2010/12/01/the-internet-is-series-of-tubes/","id":"/2010/12/01/the-internet-is-series-of-tubes","title":"The Internet is Series of Tubes (oh, and Tollgates too)\n"},{"url":"/2010/12/20/late-night-infomercials/","id":"/2010/12/20/late-night-infomercials","title":"Late-Night Infomercials: Guaranteed to Extend the 4th Amendment or Your Money Back"}],"url":"/2011/04/12/love-the-code/","date":"2011-04-12 00:00:00 +0000","id":"/2011/04/12/love-the-code","next":"/2011/04/27/fair-use-excerpting-and-copying-content-in-the-internet-ecosystem","previous":"/2011/04/04/when-all-you-have-is-a-pair-of-bolt-cutters","content":"<p>I am gave a brief <a href='http://www.meetup.com/wordpressdc/events/16887732/'>lightning talk at April&#8217;s WordPress DC Meetup</a> on the basics of HTML and PHP (&#8220;coding for dummies&#8221;). The goal: learn how to avoid breaking your website if you edit it. Below are the <a href='#deck'>slides</a> and <a href='#recording'>recording</a>.</p>\n\n<p><strong>In invite you to <a href='#deck'>watch</a>, but in short, the Cliff&#8217;s Notes are:</strong></p>\n\n<ul>\n<li>\n<p>The process</p>\n\n<ul>\n<li>The server executes PHP and outputs HTML, CSS, JavaScript, etc.<img alt='' src='http://ben.balter.com/wp-content/uploads/2011/04/infographic-300x138.png' /></li>\n\n<li>The user&#8217;s browser takes that output and renders a visual representation of the page</li>\n</ul>\n</li>\n\n<li>\n<p>Client-side Languages</p>\n\n<ul>\n<li>HTML – Static (unchanging) content; provides structure</li>\n\n<li>CSS – Provides style and form</li>\n\n<li>JavaScript – Provides interactivity</li>\n</ul>\n</li>\n\n<li>\n<p>PHP – Wrapped with &#8221;<code>php</code>&#8221; and &#8221;<code>?&gt;</code>&#8221;</p>\n\n<ul>\n<li>Variable - Text, a number, true/false, or a group of variable; identified by &#8221;<code>$</code>&#8221;</li>\n\n<li><code>If</code> Statement – performs an action <em>if</em> a statement is true</li>\n\n<li><code>While</code> Loop – performs an action <em>while</em> a statement is true</li>\n\n<li><code>For</code> / <code>Foreach</code> – combines elements of <code>while</code> and <code>if</code></li>\n\n<li>Functions – predefined set of actions; always followed by &#8221;<code>( )</code>&#8221;</li>\n\n<li>Don&#8217;t forget semicolons</li>\n</ul>\n</li>\n</ul>\n<hr />\n<p><strong>Deck</strong></p>\n\n<p><strong>Recording</strong>(I&#8217;m first up)</p>\n\n<p><strong>Links to Resources Mentioned</strong></p>\n\n<ul>\n<li>\n<p>HTML</p>\n\n<ul>\n<li><a href='http://code.google.com/edu/submissions/html-css-javascript/'>Google: HTML, CSS, &amp; js from the Ground Up</a></li>\n\n<li><a href='http://htmldog.com'>HTML Dog</a></li>\n\n<li><a href='http://www.w3.org/wiki/HTML/Training'>W3 Learning Wiki</a></li>\n\n<li><a href='http://www.w3.org/wiki/HTML/Elements'>W3 Element Wiki</a></li>\n</ul>\n</li>\n\n<li>\n<p>Text Editor</p>\n\n<ul>\n<li><a href='http://notepad-plus-plus.org/'>Notepad++</a> (Windows)</li>\n\n<li><a href='http://www.barebones.com/products/textwrangler/'>TextWrangler</a>, <a href='http://www.panic.com/coda/'>Coda</a> (Mac)</li>\n</ul>\n</li>\n\n<li>\n<p>FTP Client (to connect to server)</p>\n\n<ul>\n<li><a href='http://winscp.net/eng/index.php'>WinSCP</a>, <a href='http://notepad-plus-plus.org/'>Notepad++</a> (Windows)</li>\n\n<li><a href='http://cyberduck.ch/'>CyberDuck</a>, <a href='http://www.panic.com/coda/'>Coda</a> (Mac)</li>\n</ul>\n</li>\n\n<li>\n<p>WordPress</p>\n\n<ul>\n<li><a href='http://codex.wordpress.org/Editing_wp-config.php#Debug'>Define( WP_DEBUG, true);</a> in wp-config.php</li>\n\n<li><a href='http://wordpress.org/extend/plugins/debug-bar/'>Debug bar</a> plugin</li>\n\n<li><a href='http://codex.wordpress.org/'>WordPress Codex</a></li>\n</ul>\n</li>\n</ul>\n\n<p><em>Thanks to all who came out or tuned into the live stream. Comments? Questions? I&#8217;d love to hear your thoughts <a href='#comments'>below</a> or feel free to <a href='http://ben.balter.com/contact/'>contact me</a>.</em></p>"}